ccinput/__init__.py
ccinput/_version.py
ccinput/calculation.py
ccinput/constants.py
ccinput/documentation.py
ccinput/exceptions.py
ccinput/presets.py
ccinput/utilities.py
ccinput/verify_sanity.py
ccinput/wrapper.py
ccinput/drivers/__init__.py
ccinput/drivers/pysis.py
ccinput/packages/__init__.py
ccinput/packages/gaussian.py
ccinput/packages/nwchem.py
ccinput/packages/orca.py
ccinput/packages/psi4.py
ccinput/packages/qchem.py
ccinput/packages/xtb.py
ccinput/tests/__init__.py
ccinput/tests/test_calculation.py
ccinput/tests/test_cli.py
ccinput/tests/test_gaussian.py
ccinput/tests/test_nwchem.py
ccinput/tests/test_orca.py
ccinput/tests/test_psi4.py
ccinput/tests/test_pysis.py
ccinput/tests/test_qchem.py
ccinput/tests/test_structures.py
ccinput/tests/test_xtb.py
ccinput/tests/testing_utilities.py
ccinput-1.11.2.dist-info/LICENSE
ccinput-1.11.2.dist-info/METADATA
ccinput-1.11.2.dist-info/WHEEL
ccinput-1.11.2.dist-info/entry_points.txt
ccinput-1.11.2.dist-info/top_level.txt
ccinput-1.11.2.dist-info/RECORD
